openstats/__init__.py
openstats/app.py
openstats/cli.py
openstats/client.py
openstats/components.py
openstats/data.py
openstats/theme.py
openstats-0.1.9.3.dist-info/entry_points.txt
openstats-0.1.9.3.dist-info/LICENSE
openstats-0.1.9.3.dist-info/WHEEL
openstats-0.1.9.3.dist-info/METADATA
openstats-0.1.9.3.dist-info/RECORD
