Metadata-Version: 2.1
Name: openstats
Version: 0.1.9.3
Summary: Discover and share your OpenSource KPIs
Author-email: pmbrull <peremiquelbrull@gmail.com>
Requires-Python: >=3.6
Classifier: Development Status :: 2 - Pre-Alpha
Classifier: Intended Audience :: Developers
Classifier: License :: OSI Approved :: MIT License
Classifier: Programming Language :: Python :: 3.7
Classifier: Programming Language :: Python :: 3.8
Classifier: Programming Language :: Python :: 3.9
Classifier: Topic :: Software Development :: Libraries :: Python Modules
Requires-Dist: click==8
Requires-Dist: streamlit==1.5.0
Requires-Dist: pandas==1.3.5
Requires-Dist: requests==2.27.1
Requires-Dist: watchdog==2.1.6
Requires-Dist: levy==0.6.1
Requires-Dist: loguru==0.6.0
Requires-Dist: typer==0.4.0
Requires-Dist: black==22.1.0 ; extra == "test"
Requires-Dist: isort==5.10.1 ; extra == "test"
Requires-Dist: pylint==2.12.2 ; extra == "test"
Requires-Dist: pre-commit==2.17.0 ; extra == "test"
Project-URL: Home, https://github.com/pmbrull/open-stats
Provides-Extra: test
